{
  "project_info": {
    "project_number": "381561541061",
    "project_id": "bus-tracking-app-715be",
    "storage_bucket": "bus-tracking-app-715be.firebasestorage.app"
  },
  "client": [
    {
      "client_info": {
        "mobilesdk_app_id": "1:381561541061:android:f03e7d316e10a67435bbac",
        "android_client_info": {
          "package_name": "com.bustrackingapplication"
        }
      },
      "oauth_client": [
        {
          "client_id": "381561541061-cdsqsonqobtn27u2su7ni1jk45cs5obo.apps.googleusercontent.com",
          "client_type": 1,
          "android_info": {
            "package_name": "com.bustrackingapplication",
            "certificate_hash": "72775a6c787980ebb38f43fca4b326287f866c6d"
          }
        },
        {
          "client_id": "381561541061-dn76ahqfjmn1lnuf35ltj7cvfj4otgb5.apps.googleusercontent.com",
          "client_type": 3
        }
      ],
      "api_key": [
        {
          "current_key": "AIzaSyBPrXV81gAV_CMemaM8PLXRgTSysLnfSkQ"
        }
      ],
      "services": {
        "appinvite_service": {
          "other_platform_oauth_client": [
            {
              "client_id": "381561541061-dn76ahqfjmn1lnuf35ltj7cvfj4otgb5.apps.googleusercontent.com",
              "client_type": 3
            },
            {
              "client_id": "381561541061-3rvlggfngufim4sehkbcnhcma0t0v077.apps.googleusercontent.com",
              "client_type": 2,
              "ios_info": {
                "bundle_id": "com.bustrackingapplication.bustrackingflutter"
              }
            }
          ]
        }
      }
    },
    {
      "client_info": {
        "mobilesdk_app_id": "1:381561541061:android:25c6ca8e8dc3a59e35bbac",
        "android_client_info": {
          "package_name": "com.bustrackingapplication.bustrackingflutter"
        }
      },
      "oauth_client": [
        {
          "client_id": "381561541061-dn76ahqfjmn1lnuf35ltj7cvfj4otgb5.apps.googleusercontent.com",
          "client_type": 3
        }
      ],
      "api_key": [
        {
          "current_key": "AIzaSyBPrXV81gAV_CMemaM8PLXRgTSysLnfSkQ"
        }
      ],
      "services": {
        "appinvite_service": {
          "other_platform_oauth_client": [
            {
              "client_id": "381561541061-dn76ahqfjmn1lnuf35ltj7cvfj4otgb5.apps.googleusercontent.com",
              "client_type": 3
            },
            {
              "client_id": "381561541061-3rvlggfngufim4sehkbcnhcma0t0v077.apps.googleusercontent.com",
              "client_type": 2,
              "ios_info": {
                "bundle_id": "com.bustrackingapplication.bustrackingflutter"
              }
            }
          ]
        }
      }
    },
    {
      "client_info": {
        "mobilesdk_app_id": "1:381561541061:android:1d414630ed2d85fe35bbac",
        "android_client_info": {
          "package_name": "com.driver.bustrackingdriver"
        }
      },
      "oauth_client": [
        {
          "client_id": "381561541061-dn76ahqfjmn1lnuf35ltj7cvfj4otgb5.apps.googleusercontent.com",
          "client_type": 3
        }
      ],
      "api_key": [
        {
          "current_key": "AIzaSyBPrXV81gAV_CMemaM8PLXRgTSysLnfSkQ"
        }
      ],
      "services": {
        "appinvite_service": {
          "other_platform_oauth_client": [
            {
              "client_id": "381561541061-dn76ahqfjmn1lnuf35ltj7cvfj4otgb5.apps.googleusercontent.com",
              "client_type": 3
            },
            {
              "client_id": "381561541061-3rvlggfngufim4sehkbcnhcma0t0v077.apps.googleusercontent.com",
              "client_type": 2,
              "ios_info": {
                "bundle_id": "com.bustrackingapplication.bustrackingflutter"
              }
            }
          ]
        }
      }
    },
    {
      "client_info": {
        "mobilesdk_app_id": "1:381561541061:android:795224735624f62c35bbac",
        "android_client_info": {
          "package_name": "mobile.catchybus.catchybus"
        }
      },
      "oauth_client": [
        {
          "client_id": "381561541061-cjc5pute2q58polgbtukp1h5v3mm98ov.apps.googleusercontent.com",
          "client_type": 1,
          "android_info": {
            "package_name": "mobile.catchybus.catchybus",
            "certificate_hash": "72775a6c787980ebb38f43fca4b326287f866c6d"
          }
        },
        {
          "client_id": "381561541061-dn76ahqfjmn1lnuf35ltj7cvfj4otgb5.apps.googleusercontent.com",
          "client_type": 3
        }
      ],
      "api_key": [
        {
          "current_key": "AIzaSyBPrXV81gAV_CMemaM8PLXRgTSysLnfSkQ"
        }
      ],
      "services": {
        "appinvite_service": {
          "other_platform_oauth_client": [
            {
              "client_id": "381561541061-dn76ahqfjmn1lnuf35ltj7cvfj4otgb5.apps.googleusercontent.com",
              "client_type": 3
            },
            {
              "client_id": "381561541061-3rvlggfngufim4sehkbcnhcma0t0v077.apps.googleusercontent.com",
              "client_type": 2,
              "ios_info": {
                "bundle_id": "com.bustrackingapplication.bustrackingflutter"
              }
            }
          ]
        }
      }
    }
  ],
  "configuration_version": "1"
}
